Workbook

Sheet Assumptions
A1: FinModAI LBO Model – Key Assumptions
A3: Entry EBITDA | B3: 250000000
A4: EBITDA Margin % | B4: 0.25
A5: Entry Revenue | B5: =B3/B4
A6: Entry Multiple | B6: 10
A7: EBITDA Growth Rate | B7: 0.06
A8: Exit Multiple | B8: 11
A9: Leverage (Debt/EBITDA) | B9: 5
A10: Interest Rate | B10: 0.07
A11: Tax Rate | B11: 0.25
A12: Capex % of Revenue | B12: 0.04
A13: D&A % of Revenue | B13: 0.03
A14: NWC Change % of Revenue | B14: 0.02
A15: Hold Period (years) | B15: 5
A16: Sponsor Rollover % | B16: 0.15
A17: Fees % of EV | B17: 0.02
A18: Mandatory Amortization % of Opening Debt | B18: 0.05

Sheet Sources & Uses
A1: Sources & Uses of Funds
A3: Purchase Enterprise Value | B3: =Assumptions!$B$3*Assumptions!$B$6
A4: Transaction Fees | B4: =B3*Assumptions!$B$17
A5: Total Uses | B5: =SUM(B3:B4)
A7: Sources
A8: New Debt | B8: =Assumptions!$B$3*Assumptions!$B$9
A9: Sponsor Rollover | B9: =B3*Assumptions!$B$16
A10: Sponsor Equity | B10: =B5-B8-B9
A11: Total Sources | B11: =SUM(B8:B10)
A12: Sources minus Uses | B12: =B11-B5

Sheet LBO Cash Flows
A1: LBO Operating & Debt Schedule
B2: Year 1 | C2: Year 2 | D2: Year 3 | E2: Year 4 | F2: Year 5
A4: Revenue | B4: =Assumptions!$B$5 | C4: =B4*(1+Assumptions!$B$7) | D4: =C4*(1+Assumptions!$B$7) | E4: =D4*(1+Assumptions!$B$7) | F4: =E4*(1+Assumptions!$B$7)
A5: EBITDA | B5: =B4*Assumptions!$B$4 | C5: =C4*Assumptions!$B$4 | D5: =D4*Assumptions!$B$4 | E5: =E4*Assumptions!$B$4 | F5: =F4*Assumptions!$B$4
A6: Depreciation & Amortization | B6: =B4*Assumptions!$B$13 | C6: =C4*Assumptions!$B$13 | D6: =D4*Assumptions!$B$13 | E6: =E4*Assumptions!$B$13 | F6: =F4*Assumptions!$B$13
A7: EBIT | B7: =B5-B6 | C7: =C5-C6 | D7: =D5-D6 | E7: =E5-E6 | F7: =F5-F6
A8: Taxes | B8: =MAX(0,B7*Assumptions!$B$11) | C8: =MAX(0,C7*Assumptions!$B$11) | D8: =MAX(0,D7*Assumptions!$B$11) | E8: =MAX(0,E7*Assumptions!$B$11) | F8: =MAX(0,F7*Assumptions!$B$11)
A9: Net Operating Profit After Tax | B9: =B7-B8 | C9: =C7-C8 | D9: =D7-D8 | E9: =E7-E8 | F9: =F7-F8
A10: + Depreciation & Amortization | B10: =B6 | C10: =C6 | D10: =D6 | E10: =E6 | F10: =F6
A11: - Capital Expenditures | B11: =B4*Assumptions!$B$12 | C11: =C4*Assumptions!$B$12 | D11: =D4*Assumptions!$B$12 | E11: =E4*Assumptions!$B$12 | F11: =F4*Assumptions!$B$12
A12: - Change in Net Working Capital | B12: =B4*Assumptions!$B$14 | C12: =C4*Assumptions!$B$14 | D12: =D4*Assumptions!$B$14 | E12: =E4*Assumptions!$B$14 | F12: =F4*Assumptions!$B$14
A13: Free Cash Flow Available for Debt | B13: =B9+B10-B11-B12 | C13: =C9+C10-C11-C12 | D13: =D9+D10-D11-D12 | E13: =E9+E10-E11-E12 | F13: =F9+F10-F11-F12
A15: Debt Schedule
A16: Opening Debt Balance | B16: =Sources & Uses!$B$8 | C16: =B20 | D16: =C20 | E16: =D20 | F16: =E20
A17: Interest Expense | B17: =B16*Assumptions!$B$10 | C17: =C16*Assumptions!$B$10 | D17: =D16*Assumptions!$B$10 | E17: =E16*Assumptions!$B$10 | F17: =F16*Assumptions!$B$10
A18: Mandatory Amortization | B18: =B16*Assumptions!$B$18 | C18: =C16*Assumptions!$B$18 | D18: =D16*Assumptions!$B$18 | E18: =E16*Assumptions!$B$18 | F18: =F16*Assumptions!$B$18
A19: Optional Paydown | B19: =MIN(MAX(0,B13-B18),B16-B18) | C19: =MIN(MAX(0,C13-C18),C16-C18) | D19: =MIN(MAX(0,D13-D18),D16-D18) | E19: =MIN(MAX(0,E13-E18),E16-E18) | F19: =MIN(MAX(0,F13-F18),F16-F18)
A20: Ending Debt Balance | B20: =B16-B18-B19 | C20: =C16-C18-C19 | D20: =D16-D18-D19 | E20: =E16-E18-E19 | F20: =F16-F18-F19

Sheet Returns
A1: Sponsor Returns Summary
A3: Exit EBITDA | B3: ='LBO Cash Flows'!F5
A4: Exit Multiple | B4: =Assumptions!$B$8
A5: Exit Enterprise Value | B5: =B3*B4
A6: Ending Net Debt | B6: ='LBO Cash Flows'!F20
A7: Equity Value to Sponsor | B7: =B5-B6
A8: Sponsor Equity Invested | B8: ='Sources & Uses'!$B$10
A9: MOIC | B9: =B7/B8
A10: IRR | B10: =IRR(B14:G14)
A12: Sponsor Cash Flows
B13: Year 0 | C13: Year 1 | D13: Year 2 | E13: Year 3 | F13: Year 4 | G13: Year 5 | H13: Year 6
B14: =-'Sources & Uses'!$B$10 | C14: 0 | D14: 0 | E14: 0 | F14: 0 | G14: 0 | H14: =B7
