Workbook

Sheet Assumptions
A1: FinModAI DCF Model – Key Assumptions
A3: Starting Free Cash Flow | B3: 150000
A4: Year 1 FCF Growth % | B4: 0.12
A5: Year 2 FCF Growth % | B5: 0.1
A6: Year 3 FCF Growth % | B6: 0.08
A7: Year 4 FCF Growth % | B7: 0.06
A8: Year 5 FCF Growth % | B8: 0.05
A9: Weighted Average Cost of Capital (WACC) | B9: 0.09
A10: Terminal Growth Rate (g) | B10: 0.025
A11: Net Debt | B11: 275000
A12: Shares Outstanding (mm) | B12: 80

Sheet DCF
A1: Discounted Cash Flow Analysis (USD)
B2: Year 1 | C2: Year 2 | D2: Year 3 | E2: Year 4 | F2: Year 5
A4: Free Cash Flow | B4: =Assumptions!$B$3*(1+Assumptions!$B$4) | C4: =B4*(1+Assumptions!$B$5) | D4: =C4*(1+Assumptions!$B$6) | E4: =D4*(1+Assumptions!$B$7) | F4: =E4*(1+Assumptions!$B$8)
A5: Growth Rate | B5: =Assumptions!$B$4 | C5: =Assumptions!$B$5 | D5: =Assumptions!$B$6 | E5: =Assumptions!$B$7 | F5: =Assumptions!$B$8
A6: Discount Factor | B6: =1/POWER(1+Assumptions!$B$9,1) | C6: =1/POWER(1+Assumptions!$B$9,2) | D6: =1/POWER(1+Assumptions!$B$9,3) | E6: =1/POWER(1+Assumptions!$B$9,4) | F6: =1/POWER(1+Assumptions!$B$9,5)
A7: Present Value of FCF | B7: =B4*B6 | C7: =C4*C6 | D7: =D4*D6 | E7: =E4*E6 | F7: =F4*F6
A8: Terminal Value | F8: =F4*(1+Assumptions!$B$10)/(Assumptions!$B$9-Assumptions!$B$10)
A9: PV of Terminal Value | F9: =F8*F6
A12: Valuation Summary
A13: PV of Explicit Free Cash Flows | B13: =SUM(B7:F7)
A14: PV of Terminal Value | B14: =F9
A15: Enterprise Value | B15: =B13+B14
A16: Less: Net Debt | B16: =Assumptions!$B$11
A17: Equity Value | B17: =B15-B16
A18: Shares Outstanding (mm) | B18: =Assumptions!$B$12
A19: Implied Price per Share | B19: =B17/B18
